kivy_garden/contextmenu/__init__.py
kivy_garden/contextmenu/_version.py
kivy_garden/contextmenu/app_menu.kv
kivy_garden/contextmenu/app_menu.py
kivy_garden/contextmenu/context_menu.kv
kivy_garden/contextmenu/context_menu.py
kivy_garden.contextmenu-0.1.0.dev1.dist-info/AUTHORS.txt
kivy_garden.contextmenu-0.1.0.dev1.dist-info/LICENSE.txt
kivy_garden.contextmenu-0.1.0.dev1.dist-info/METADATA
kivy_garden.contextmenu-0.1.0.dev1.dist-info/WHEEL
kivy_garden.contextmenu-0.1.0.dev1.dist-info/top_level.txt
kivy_garden.contextmenu-0.1.0.dev1.dist-info/RECORD
